AUTHORS
CHANGELOG.rst
LICENSE
MANIFEST.in
README
README.rst
requirements.txt
setup.cfg
setup.py
docs/CHANGELOG.rst
docs/CONTRIBUTING.rst
docs/LICENSE.rst
docs/README.rst
docs/conf.py
docs/index.rst
docs/html/index.html
freecell_solver/__init__.py
freecell_solver/__main__.py
freecell_solver/template.py
freecell_solver.egg-info/PKG-INFO
freecell_solver.egg-info/SOURCES.txt
freecell_solver.egg-info/dependency_links.txt
freecell_solver.egg-info/entry_points.txt
freecell_solver.egg-info/not-zip-safe
freecell_solver.egg-info/requires.txt
freecell_solver.egg-info/top_level.txt
tests/__init__.py
tests/test_sanity.py